antifold/__init__.py
antifold/antiscripts.py
antifold/esm_multichain_util_custom.py
antifold/esm_util_custom.py
antifold/if1_dataset.py
antifold/main copy.py
antifold/main.py
antifold/esm/__init__.py
antifold/esm/constants.py
antifold/esm/data.py
antifold/esm/modules.py
antifold/esm/multihead_attention.py
antifold/esm/pretrained.py
antifold/esm/rotary_embedding.py
antifold/esm/inverse_folding/__init__.py
antifold/esm/inverse_folding/features.py
antifold/esm/inverse_folding/gvp_encoder.py
antifold/esm/inverse_folding/gvp_modules.py
antifold/esm/inverse_folding/gvp_transformer.py
antifold/esm/inverse_folding/gvp_transformer_encoder.py
antifold/esm/inverse_folding/gvp_utils.py
antifold/esm/inverse_folding/multichain_util.py
antifold/esm/inverse_folding/transformer_decoder.py
antifold/esm/inverse_folding/transformer_layer.py
antifold/esm/inverse_folding/util.py
antifold-0.3.1.dist-info/LICENSE
antifold-0.3.1.dist-info/METADATA
antifold-0.3.1.dist-info/WHEEL
antifold-0.3.1.dist-info/top_level.txt
antifold-0.3.1.dist-info/RECORD
