Metadata-Version: 2.1
Name: antifold
Version: 0.3.1
Summary: Inverse folding of antibodies
Home-page: https://github.com/oxpig/AntiFold/
Author: Magnus Haraldson Høie & Alissa Hummer
Author-email: maghoi@dtu.dk
Classifier: Development Status :: 5 - Production/Stable
Classifier: Intended Audience :: Science/Research
Classifier: Operating System :: POSIX :: Linux
Classifier: Programming Language :: Python :: 3.10
License-File: LICENSE
Requires-Dist: torch-geometric ==2.4.0
Requires-Dist: torch ==2.3.1
Requires-Dist: biopython ==1.83
Requires-Dist: biotite ==0.38
Requires-Dist: pygam ==0.9.*
Requires-Dist: numpy ==1.26.*
Requires-Dist: pandas ==2.*
